pyjs/__init__.py
pyjs/decorator.py
pyjs/jsbuilder.py
pyjs/pillar.py
pyjs/registry.py
pyjs/transport/__init__.py
pyjs/transport/proto.js
pyjs/transport/websocket.py
pyjs_bridge-1.0.dist-info/LICENSE
pyjs_bridge-1.0.dist-info/METADATA
pyjs_bridge-1.0.dist-info/WHEEL
pyjs_bridge-1.0.dist-info/top_level.txt
pyjs_bridge-1.0.dist-info/RECORD
